[
    {
        "id": "0",
        "label": "健康指南",
        "description": ""
    },
    {
        "id": "1",
        "label": "饮食与营养",
        "description": ""
    },
    {
        "id": "2",
        "label": "健康饮食的原则",
        "description": "健康饮食的原则包括均衡摄入蛋白质、碳水化合物、脂肪，以及多摄入水果蔬菜，减少糖和盐的摄入。"
    },
    {
        "id": "3",
        "label": "均衡饮食",
        "description": ""
    },
    {
        "id": "4",
        "label": "低糖低盐",
        "description": ""
    },
    {
        "id": "5",
        "label": "常见的营养素及其作用",
        "description": "常见的营养素包括蛋白质、碳水化合物、脂肪、维生素和矿物质，每种营养素对身体的健康都有不同的作用。"
    },
    {
        "id": "6",
        "label": "蛋白质",
        "description": ""
    },
    {
        "id": "7",
        "label": "维生素",
        "description": ""
    },
    {
        "id": "8",
        "label": "运动与健身",
        "description": ""
    },
    {
        "id": "9",
        "label": "日常锻炼的重要性",
        "description": "日常锻炼有助于增强心血管健康、控制体重、提升心理健康，并降低患慢性疾病的风险。"
    },
    {
        "id": "10",
        "label": "心血管健康",
        "description": ""
    },
    {
        "id": "11",
        "label": "慢性疾病预防",
        "description": ""
    },
    {
        "id": "12",
        "label": "常见的锻炼方式",
        "description": "常见的锻炼方式包括有氧运动（如跑步、游泳）、力量训练（如举重）以及柔韧性训练（如瑜伽）。"
    },
    {
        "id": "13",
        "label": "有氧运动",
        "description": ""
    },
    {
        "id": "14",
        "label": "力量训练",
        "description": ""
    },
    {
        "id": "15",
        "label": "心理健康",
        "description": ""
    },
    {
        "id": "16",
        "label": "管理压力的技巧",
        "description": "管理压力的技巧包括深呼吸、冥想、规律作息、保持积极的社交关系，以及寻求专业帮助。"
    },
    {
        "id": "17",
        "label": "冥想",
        "description": ""
    },
    {
        "id": "18",
        "label": "社交支持",
        "description": ""
    },
    {
        "id": "19",
        "label": "常见的心理健康问题",
        "description": "常见的心理健康问题包括抑郁症、焦虑症、强迫症和压力相关障碍等，这些问题可能影响日常生活质量。"
    },
    {
        "id": "20",
        "label": "抑郁症",
        "description": ""
    },
    {
        "id": "21",
        "label": "焦虑症",
        "description": ""
    },
    {
        "id": "22",
        "label": "疾病预防",
        "description": ""
    },
    {
        "id": "23",
        "label": "疫苗接种的重要性",
        "description": "疫苗接种是预防传染病的有效方式，通过建立群体免疫，减少疾病传播。"
    },
    {
        "id": "24",
        "label": "传染病",
        "description": ""
    },
    {
        "id": "25",
        "label": "群体免疫",
        "description": ""
    },
    {
        "id": "26",
        "label": "常见病的预防措施",
        "description": "常见病的预防措施包括保持良好的卫生习惯、定期体检、健康饮食以及适量运动。"
    },
    {
        "id": "27",
        "label": "良好卫生习惯",
        "description": ""
    },
    {
        "id": "28",
        "label": "定期体检",
        "description": ""
    }
]